TablaPos 4/TablaPos4.v

module gates();

// declaración de variables

wire O1;
wire O2;
wire O3;
wire O4;
wire O5;
wire O6;
wire O7;
wire O8;
wire O9;		//or necesarios
wire Y;		//and necesario
wire NA;
wire NB;
wire NC;
wire ND;		//not necesarios
reg A, B, C, D;	// entradas

// declaracion de gates
not GNA (NA, A);		//-A
not GNB (NB, B);		//-B
not GNC (NC, C);		//-C
not GND (ND, D);		//-D
or GO1 (O1, A,B,C,ND);		//A+B+C-D
or GO2 (O2, A,NB,C,D);		//A-B+C+D
or GO3 (O3, A,NB,C,ND);		//A-B+C-D
or GO4 (O4, NA,B,C,ND);	//-A+B+C-D
or GO5 (O5, NA,B,NC,ND);		//-A+B-C-D
or GO6 (O6, NA,NB,C,D);	//-A-B+C+D
or GO7 (O7, NA,NB,C,ND);		//-A-B+C-D
or GO8 (O8, NA,NB,NC,D);	//-A-B-C+D
or GO9 (O9, NA,NB,NC,ND);	//-A-B-C-D
and GA1 (Y, O1, O2, O3, O4, O5, O6, O7, O8, O9);	//respuesta


// inicio
initial begin
$display("A B C D | Y");
$display("-------");
//declaramos tipo de variable

  $monitor("%b %b %b %b | %b", A, B, C, D, Y);

  // Inpunts en 0
  A = 0;
  B = 0;
  C = 0;
  D = 0;

  // Declaramos otros cambios en otros tiempo
  #1 D=1;
  #1 C=1;D=0;
  #1 D=1;
  #1 B=1;C=0;D=0;
  #1 D=1;
  #1 C=1;D=0;
  #1 D=1;
  #1 A=1;B=0;C=0;D=0;
  #1 D=1;
  #1 C=1;D=0;
  #1 D=1;
  #1 B=1;C=0;D=0;
  #1 D=1;
  #1 C=1;D=0;
  #1 D=1;
  #1 $finish;   // termina la simulación
end


  initial
    begin
      $dumpfile("top_tb.vcd"); // noten que el nombre del archivo siempre es el que incluye el _tb y la extension es .vcd
      $dumpvars(0, gates); // noten que el nombre que está después del número 0 es el mismo que el nombre del módulo que estamos probando
    end
endmodule	//finalizar el módulo

TablaPos 4/TablaPos4_tb.vcd
$date
	Fri Jul 31 07:49:28 2020
$end
$version
	Icarus Verilog
$end
$timescale
	1ps
$end
$scope module gates $end
$var wire 1 ! NA $end
$var wire 1 " NB $end
$var wire 1 # NC $end
$var wire 1 $ ND $end
$var wire 1 % O1 $end
$var wire 1 & O2 $end
$var wire 1 ' O3 $end
$var wire 1 ( O4 $end
$var wire 1 ) O5 $end
$var wire 1 * O6 $end
$var wire 1 + O7 $end
$var wire 1 , O8 $end
$var wire 1 - O9 $end
$var wire 1 . Y $end
$var reg 1 / A $end
$var reg 1 0 B $end
$var reg 1 1 C $end
$var reg 1 2 D $end
$upscope $end
$enddefinitions $end
#0
$dumpvars
02
01
00
0/
1.
1-
1,
1+
1*
1)
1(
1'
1&
1%
1$
1#
1"
1!
$end
#1
0.
0%
0$
12
#2
1.
1$
1%
0#
02
11
#3
0$
12
#4
0.
1$
1'
0&
1#
0"
02
01
10
#5
0'
1&
0$
12
#6
1.
1$
1'
0#
02
11
#7
0$
12
#8
1.
1$
1#
1)
1(
1"
0!
02
01
00
1/
#9
0.
0(
0$
12
#10
1.
1$
1(
0#
02
11
#11
0.
0)
0$
12
#12
1$
1+
0*
1#
1)
0"
02
01
10
#13
0+
1*
0$
12
#14
0,
1$
1+
0#
02
11
#15
0-
1,
0$
12
