TablaSop 2/TablaSop2.v

module gates();

// declaración de variables

wire A1;
wire A2;
wire A3;		//AND necesarios
wire Y;		//or necesario
wire NA;
wire NB;
wire NC;		//not necesarios
reg A, B, C;	// entradas

// declaracion de gates
not GNA (NA, A);		//-A
not GNB (NB, B);		//-B
not GNC (NC, C);		//-C
and GA1 (A1, NA,NB,C);		 //-A-BC
and GA2 (A2, A,B,NC);		//AB-C
and GA3 (A3, A,B,C);		//ABC
or GO1 (Y, A1, A2, A3);	//respuesta


// inicio
initial begin
$display("A B C | Y");
$display("-------");
//declaramos tipo de variable

  $monitor("%b %b %b | %b", A, B, C, Y);

  // Inpunts en 0
  A = 0;
  B = 0;
  C = 0;

  // Declaramos otros cambios en otros tiempo
  #1 C = 1;
  #1 B = 1; C=0;
  #1 C = 1;
  #1 A=1;B=0;C=0;
  #1 C=1;
  #1 B=1;C=0;
  #1 C=1;
  #1 $finish;   // termina la simulación
end


  initial
    begin
      $dumpfile("top_tb.vcd"); // noten que el nombre del archivo siempre es el que incluye el _tb y la extension es .vcd
      $dumpvars(0, gates); // noten que el nombre que está después del número 0 es el mismo que el nombre del módulo que estamos probando
    end
endmodule	//finalizar el módulo

TablaSop 2/TablaSop2_tb.vcd
$date
	Fri Jul 31 07:56:45 2020
$end
$version
	Icarus Verilog
$end
$timescale
	1ps
$end
$scope module gates $end
$var wire 1 ! A1 $end
$var wire 1 " A2 $end
$var wire 1 # A3 $end
$var wire 1 $ NA $end
$var wire 1 % NB $end
$var wire 1 & NC $end
$var wire 1 ' Y $end
$var reg 1 ( A $end
$var reg 1 ) B $end
$var reg 1 * C $end
$upscope $end
$enddefinitions $end
#0
$dumpvars
0*
0)
0(
0'
1&
1%
1$
0#
0"
0!
$end
#1
1'
1!
0&
1*
#2
0'
0!
1&
0%
0*
1)
#3
0&
1*
#4
1&
1%
0$
0*
0)
1(
#5
0&
1*
#6
1'
1"
1&
0%
0*
1)
#7
0"
1#
0&
1*
