TablaSop 4/TablaSop4.v

module gates();

// declaración de variables

wire A1;
wire A2;
wire A3;
wire A4;
wire A5;
wire A6;
wire A7;		//AND necesarios
wire Y;		//or necesario
wire NA;
wire NB;
wire NC;
wire ND;		//not necesarios
reg A, B, C, D;	// entradas

// declaracion de gates
not GNA (NA, A);		//-A
not GNB (NB, B);		//-B
not GNC (NC, C);		//-C
not GND (ND, D);		//-D
and GA1 (A1, NA,NB,NC,ND);	//-A-B-C-D
and GA2 (A2, NA,NB,C,ND);	//-A-BC-D
and GA3 (A3, NA,NB,C,D);	//-A-BCD
and GA4 (A4, NA,B,C,ND);	//-ABC-D
and GA5 (A5, NA,B,C,D);		//-ABCD
and GA6 (A6, A,NB,NC,ND);	//A-B-C-D
and GA7 (A7, A,NB,C,ND);		//A-BC-D
or GO1 (Y, A1, A2, A3, A4, A5, A6, A7);	//respuesta


// inicio
initial begin
$display("A B C D | Y");
$display("-------");
//declaramos tipo de variable

  $monitor("%b %b %b %b | %b", A, B, C, D, Y);

  // Inpunts en 0
  A = 0;
  B = 0;
  C = 0;
  D = 0;

  // Declaramos otros cambios en otros tiempo
  #1 D=1;
  #1 C=1;D=0;
  #1 D=1;
  #1 B=1;C=0;D=0;
  #1 D=1;
  #1 C=1;D=0;
  #1 D=1;
  #1 A=1;B=0;C=0;D=0;
  #1 D=1;
  #1 C=1;D=0;
  #1 D=1;
  #1 B=1;C=0;D=0;
  #1 D=1;
  #1 C=1;D=0;
  #1 D=1;
  #1 $finish;   // termina la simulación
end


  initial
    begin
      $dumpfile("top_tb.vcd"); // noten que el nombre del archivo siempre es el que incluye el _tb y la extension es .vcd
      $dumpvars(0, gates); // noten que el nombre que está después del número 0 es el mismo que el nombre del módulo que estamos probando
    end
endmodule	//finalizar el módulo

TablaSop 4/TablaSop4_tb.vcd
$date
	Fri Jul 31 07:59:39 2020
$end
$version
	Icarus Verilog
$end
$timescale
	1ps
$end
$scope module gates $end
$var wire 1 ! A1 $end
$var wire 1 " A2 $end
$var wire 1 # A3 $end
$var wire 1 $ A4 $end
$var wire 1 % A5 $end
$var wire 1 & A6 $end
$var wire 1 ' A7 $end
$var wire 1 ( NA $end
$var wire 1 ) NB $end
$var wire 1 * NC $end
$var wire 1 + ND $end
$var wire 1 , Y $end
$var reg 1 - A $end
$var reg 1 . B $end
$var reg 1 / C $end
$var reg 1 0 D $end
$upscope $end
$enddefinitions $end
#0
$dumpvars
00
0/
0.
0-
1,
1+
1*
1)
1(
0'
0&
0%
0$
0#
0"
1!
$end
#1
0,
0!
0+
10
#2
1,
1"
1+
0*
00
1/
#3
0"
1#
0+
10
#4
0,
1+
0#
1*
0)
00
0/
1.
#5
0+
10
#6
1,
1$
1+
0*
00
1/
#7
0$
1%
0+
10
#8
1&
1+
1*
0%
1)
0(
00
0/
0.
1-
#9
0,
0&
0+
10
#10
1,
1'
1+
0*
00
1/
#11
0,
0'
0+
10
#12
1+
1*
0)
00
0/
1.
#13
0+
10
#14
1+
0*
00
1/
#15
0+
10
