TablaPos 1/TablaPos1.v

module gates();

// declaración de variables

wire O1;
wire O2;
wire O3;		//or necesarios
wire A1;		//and necesario
wire N1;
wire N2;
wire N3;		//not necesarios
reg A, B, C;	// entradas

// declaracion de gates
not GNA (N1, A);		//-A
not GNB (N2, B);		//-B
not GNC (N3, C);		//-C
or GO1 (O1, A,B,N3);		 //A+B-C
or GO2 (O2, A,N2,N3);		//A-B-C
or GO3 (O3, N1,N2,C);		//-A-B+C
and GA1 (A1, O1, O2, O3);	//respuesta


// inicio
initial begin
$display("A B C | Y");
$display("-------");
//declaramos tipo de variable

  $monitor("%b %b %b | %b", A, B, C, A1);

  // Inpunts en 0
  A = 0;
  B = 0;
  C = 0;

  // Declaramos otros cambios en otros tiempo
  #1 C = 1;
  #1 B = 1; C=0;
  #1 C = 1;
  #1 A=1;B=0;C=0;
  #1 C=1;
  #1 B=1;C=0;
  #1 C=1;
  #1 $finish;   // termina la simulación
end


  initial
    begin
      $dumpfile("top_tb.vcd"); // noten que el nombre del archivo siempre es el que incluye el _tb y la extension es .vcd
      $dumpvars(0, gates); // noten que el nombre que está después del número 0 es el mismo que el nombre del módulo que estamos probando
    end
endmodule	//finalizar el módulo

TablaPos 1/TablaPos1_tb.vcd
$date
	Fri Jul 31 07:37:21 2020
$end
$version
	Icarus Verilog
$end
$timescale
	1ps
$end
$scope module gates $end
$var wire 1 ! A1 $end
$var wire 1 " N1 $end
$var wire 1 # N2 $end
$var wire 1 $ N3 $end
$var wire 1 % O1 $end
$var wire 1 & O2 $end
$var wire 1 ' O3 $end
$var reg 1 ( A $end
$var reg 1 ) B $end
$var reg 1 * C $end
$upscope $end
$enddefinitions $end
#0
$dumpvars
0*
0)
0(
1'
1&
1%
1$
1#
1"
1!
$end
#1
0!
0%
0$
1*
#2
1!
1$
1%
0#
0*
1)
#3
0!
0&
0$
1*
#4
1!
1$
1#
1&
0"
0*
0)
1(
#5
0$
1*
#6
0!
0'
1$
0#
0*
1)
#7
1!
1'
0$
1*
